[
  {
    "name": "Asparagus Soup",
    "hp": 20,
    "hunger": 18.75,
    "sanity": 5,
		"rot": 15,
		"ismeat": false,
		"img": "./images/crockpot/asparagussoup.png",
		"recipes": [
			["asparagus", "veggies", "any", "any"],
			["asparagus", "carrot", "redcap", "redcap"]
		],
		"restrictions": [
			"twigs"
		],
		"notes": "Low value food, Asparagus better used in Vegetable Stinger"
  },
  {
    "name": "Bacon and Eggs",
    "hp": 20,
    "hunger": 75,
    "sanity": 5,
		"rot": 20,
		"ismeat": true,
		"img": "./images/crockpot/baconandeggs.png",
		"recipes": [
			["meats", "meats", "egg", "egg"],
			["morsel", "monstermeat", "tallbirdegg", "any"]
		],
		"restrictions": [
			"veggies"
		],
		"notes": "Decent all round food with high stats and rot time. Wilson's favorite food."
  },
  {
    "name": "Banana Pop",
    "hp": 20,
    "hunger": 12.5,
    "sanity": 33,
		"rot": 3,
		"ismeat": false,
		"img": "./images/crockpot/bananapop.png",
		"recipes": [
			["banana", "ice", "twigs", "any"],
			["banana", "ice", "twigs", "twigs"]
		],
		"restrictions": [
			"meats", "fishes"
		],
		"notes": "Bring some ice down to the ruins to make these. Wendy's favorite food."
  },
  {
    "name": "Butter Muffin",
    "hp": 20,
    "hunger": 37.5,
    "sanity": 5,
		"rot": 15,
		"ismeat": false,
		"img": "./images/crockpot/buttermuffin.png",
		"recipes": [
			["butterflywings", "veggies", "any", "any"],
			["butterflywings", "redcap", "twigs", "twigs"]
		],
		"restrictions": [
			"meats"
		],
		"notes": "Decent healing item early-game. WX-78's favorite food."
  },
  {
    "name": "California Roll",
    "hp": 20,
    "hunger": 37.5,
    "sanity": 10,
		"rot": 10,
		"ismeat": true,
		"img": "./images/crockpot/californiaroll.png",
		"recipes": [
			["fishes", "seaweed", "seaweed", "any"],
			["freshwaterfish", "freshwaterfish", "seaweed", "seaweed"],
			["eel", "seaweed", "seaweed", "twigs"]
		],
		"restrictions": [
			"none"
		],
		"notes": "Low-value food, not recommended unless you need the health."
  },
  {
    "name": "Ceviche",
    "hp": 20,
    "hunger": 25,
    "sanity": 5,
		"rot": 10,
		"ismeat": true,
		"img": "./images/crockpot/ceviche.png",
		"recipes": [
			["fishes", "fishes", "ice", "any"],
			["freshwaterfish", "freshwaterfish", "ice", "berries"]
		],
		"restrictions": [
			"none"
		],
		"notes": "Low-value food, not recommended unless you need the health."
  },
  {
    "name": "Creamy Potato Puree",
    "hp": 20,
    "hunger": 37.5,
    "sanity": 33,
		"rot": 15,
		"ismeat": false,
		"img": "./images/crockpot/creamypotatopuree.png",
		"recipes": [
			["potato", "potato", "garlic", "any"],
			["potato", "potato", "garlic", "honey"]
		],
		"restrictions": [
			"twigs", "meats"
		],
		"notes": "Low value food, just cook and eat the two potato for more hp and hunger."
  },
  {
    "name": "Dragonpie",
    "hp": 40,
    "hunger": 75,
    "sanity": 5,
		"rot": 15,
		"ismeat": false,
		"img": "./images/crockpot/dragonpie.png",
		"recipes": [
			["dragonfruit", "any", "any", "any"],
			["dragonfruit", "twigs", "twigs", "twigs"]
		],
		"restrictions": [
			"meats", "asparagus"
		],
		"notes": "Arguably the best food in the game, dedicate your farms to dragonfruit as early as possible"
  },
  {
    "name": "Fancy Spiralled Tubers",
    "hp": 3,
    "hunger": 37.5,
    "sanity": 15,
		"rot": 10,
		"ismeat": false,
		"img": "./images/crockpot/fancyspiralledtubers.png",
		"recipes": [
			["potato", "twigs", "any", "any"],
			["potato", "twigs", "twigs", "any"]
		],
		"restrictions": [
			"meats", "twigs", "twigs", "twigs"
		],
		"notes": "Low value food, will not work with 3 twigs."
  },
  {
    "name": "Fish Tacos",
    "hp": 20,
    "hunger": 37.5,
    "sanity": 5,
		"rot": 6,
		"ismeat": true,
		"img": "./images/crockpot/fishtacos.png",
		"recipes": [
			["fishes", "corn", "any", "any"],
			["fishes", "corn", "twigs", "twigs"]
		],
		"restrictions": [
			"none"
		],
		"notes": "Low value food, fish and corn both have more useful recipes."
  },
  {
    "name": "Fish Sticks",
    "hp": 40,
    "hunger": 37.5,
    "sanity": 5,
		"rot": 10,
		"ismeat": true,
		"img": "./images/crockpot/fishsticks.png",
		"recipes": [
			["fishes", "twigs", "any", "any"],
			["fishes", "twigs", "monstermeat", "monstermeat"]
		],
		"restrictions": [
			"moleworm", "twigs", "twigs"
		],
		"notes": "Great health recovery food, one of the few recipes that works with two monster meat."
  },
  {
    "name": "Fist Full of Jam",
    "hp": 3,
    "hunger": 37.5,
    "sanity": 5,
		"rot": 15,
		"ismeat": false,
		"img": "./images/crockpot/fistfullofjam.png",
		"recipes": [
			["fruits", "any", "any", "any"],
			["berries", "berries", "berries", "berries"]
		],
		"restrictions": [
			"meats", "veggies", "twigs"
		],
		"notes": "Unless you're Wurt, or you've got tons of spoiled berries, avoid cooking this."
  },
  {
    "name": "Flower Salad",
    "hp": 40,
    "hunger": 12.5,
    "sanity": 5,
		"rot": 6,
		"ismeat": false,
		"img": "./images/crockpot/flowersalad.png",
		"recipes": [
			["cactusflower", "veggies", "any", "any"]
		],
		"restrictions": [
			"meats", "fruits", "egg", "twigs", "honey"
		],
		"notes": "Not bad for health recovery, fast spoil time though."
  },
  {
    "name": "Froggle Bunwich",
    "hp": 20,
    "hunger": 37.5,
    "sanity": 5,
		"rot": 15,
		"ismeat": true,
		"img": "./images/crockpot/froggiebunwich.png",
		"recipes": [
			["froglegs", "veggies", "any", "any"],
			["froglegs", "carrot", "twigs", "twigs"]
		],
		"restrictions": [
			"egg", "honey"
		],
		"notes": "Not the worst use of frog legs and a carrot, but far from the best healing food."
  },
  {
    "name": "Fruit Medley",
    "hp": 20,
    "hunger": 25,
    "sanity": 5,
		"rot": 6,
		"ismeat": false,
		"img": "./images/crockpot/fruitmedley.png",
		"recipes": [
			["fruits", "fruits", "fruits", "any"],
			["durian", "durian", "durian", "twigs"]
		],
		"restrictions": [
			"dragonfruit", "meats", "veggies"
		],
		"notes": "Low value food, not recommended under any circumstance."
  },
  {
    "name": "Guacamole",
    "hp": 20,
    "hunger": 37.5,
    "sanity": 0,
		"rot": 10,
		"ismeat": true,
		"img": "./images/crockpot/guacamole.png",
		"recipes": [
			["moleworm", "cactus", "any", "any"],
			["moleworm", "stonefruit", "any", "any"]
		],
		"restrictions": [
			"fruits"
		],
		"notes": "Low value food, not recommended under any circumstance."
  },
  {
    "name": "Honey Ham",
    "hp": 30,
    "hunger": 75,
    "sanity": 5,
		"rot": 15,
		"ismeat": true,
		"img": "./images/crockpot/honeyham.png",
		"recipes": [
			["meats", "meats", "honey", "any"],
			["meat", "monstermeat", "honey", "any"]
		],
		"restrictions": [
			"twigs", "moleworm", "tallbirdegg"
		],
		"notes": "One of the best foods in the game, on par with Dragonfruit Pie."
  },
  {
    "name": "Honey Nuggets",
    "hp": 20,
    "hunger": 37.5,
    "sanity": 5,
		"rot": 15,
		"ismeat": true,
		"img": "./images/crockpot/honeynuggets.png",
		"recipes": [
			["meats", "honey", "any", "any"],
			["monstermeat", "honey", "berries", "berries"]
		],
		"restrictions": [
			"twigs"
		],
		"notes": "Low value food, not recommended unless you're playing as Woodie. Woodie's favorite food."
  },
  {
    "name": "Ice Cream",
    "hp": 0,
    "hunger": 25,
    "sanity": 50,
		"rot": 3,
		"ismeat": false,
		"img": "./images/crockpot/icecream.png",
		"recipes": [
			["electricmilk", "honey", "ice", "any"],
			["butter", "honey", "ice", "any"]
		],
		"restrictions": [
			"meats", "egg", "veggies", "twigs"
		],
		"notes": "Best sanity recovery item in the game, low stats across the board otherwise."
  },
  {
    "name": "Jelly Beans",
    "hp": "122",
    "hunger": 0,
    "sanity": 5,
		"rot": "N/A",
		"ismeat": false,
		"img": "./images/crockpot/jellybeans.png",
		"recipes": [
			["royaljelly", "any", "any", "any"],
			["royaljelly", "ice", "ice", "ice"]
		],
		"restrictions": [
			"monsterfoods", "twigs"
		],
		"notes": "HP bonus heals over time, very good for boss fights, and only use for royal jelly."
  },
  {
    "name": "Kabobs",
    "hp": 3,
    "hunger": 37.5,
    "sanity": 5,
		"rot": 15,
		"ismeat": true,
		"img": "./images/crockpot/kabobs.png",
		"recipes": [
			["meats", "twigs", "any", "any"],
			["monstermeat", "twigs", "berries", "berries"]
		],
		"restrictions": [
			"fishes", "moleworm", "twigs", "twigs"
		],
		"notes": "x"
  },
  {
    "name": "Lobster Bisque",
    "hp": 60,
    "hunger": 25,
    "sanity": 10,
		"rot": 10,
		"ismeat": true,
		"img": "./images/crockpot/lobsterbisque.png",
		"recipes": [
			["wobster", "ice", "any", "any"],
			["wobster", "ice", "monstermeat", "monstermeat"]
		],
		"restrictions": [
			"none"
		],
		"notes": "x"
  },
  {
    "name": "Lobster Dinner",
    "hp": 60,
    "hunger": 37.5,
    "sanity": 50,
		"rot": 15,
		"ismeat": true,
		"img": "./images/crockpot/lobsterdinner.png",
		"recipes": [
			["wobster", "butter", "any", "any"],
			["wobster", "butter", "twigs", "twigs"]
		],
		"restrictions": [
			"meats", "fishes", "ice"
		],
		"notes": "x"
  },
  {
    "name": "Mandrake Soup",
    "hp": 100,
    "hunger": 150,
    "sanity": 5,
		"rot": 6,
		"ismeat": false,
		"img": "./images/crockpot/mandrakesoup.png",
		"recipes": [
			["mandrake", "any", "any", "any"],
			["mandrake", "twigs", "twigs", "twigs"]
		],
		"restrictions": [
			"none"
		],
		"notes": "x"
  },
  {
    "name": "Meatballs",
    "hp": 3,
    "hunger": 62.5,
    "sanity": 5,
		"rot": 10,
		"ismeat": true,
		"img": "./images/crockpot/meatballs.png",
		"recipes": [
			["meats", "any", "any", "any"],
			["fishes", "any", "any", "any"]
		],
		"restrictions": [
			"twigs", "honey"
		],
		"notes": "x"
  },
  {
    "name": "Meaty Stew",
    "hp": 12,
    "hunger": 150,
    "sanity": 5,
		"rot": 10,
		"ismeat": true,
		"img": "./images/crockpot/meatystew.png",
		"recipes": [
			["meat", "meats", "meats", "any"],
			["meat", "meat", "monstermeat", "ice"]
		],
		"restrictions": [
			"twigs", "moleworm", "honey", "tallbirdegg"
		],
		"notes": "x"
  },
  {
    "name": "Melonsicle",
    "hp": 3,
    "hunger": 12.5,
    "sanity": 20,
		"rot": 3,
		"ismeat": false,
		"img": "./images/crockpot/melonsicle.png",
		"recipes": [
			["watermelon", "ice", "twigs", "any"],
			["watermelon", "ice", "twigs", "twigs"]
		],
		"restrictions": [
			"meats", "veggies", "egg"
		],
		"notes": "x"
  },
  {
    "name": "Monster Lasagna",
    "hp": -20,
    "hunger": 37.5,
    "sanity": -20,
		"rot": 6,
		"ismeat": true,
		"img": "./images/crockpot/monsterlasagne.png",
		"recipes": [
			["monsterfoods", "monsterfoods", "any", "any"],
			["monstermeat", "durian", "any", "any"]
		],
		"restrictions": [
			"twigs"
		],
		"notes": "x"
  },
  {
    "name": "Pierogi",
    "hp": 40,
    "hunger": 37.5,
    "sanity": 5,
		"rot": 20,
		"ismeat": true,
		"img": "./images/crockpot/pierogi.png",
		"recipes": [
			["meats", "egg", "veggies", "any"],
			["monstermeat", "egg", "carrot", "ice"]
		],
		"restrictions": [
			"moleworm", "twigs"
		],
		"notes": "x"
  },
  {
    "name": "Powdercake",
    "hp": -3,
    "hunger": 0,
    "sanity": 0,
		"rot": 18750,
		"ismeat": false,
		"img": "./images/crockpot/powdercake.png",
		"recipes": [
			["corn", "honey", "twigs", "any"],
			["corn", "honey", "twigs", "twigs"]
		],
		"restrictions": [
			"none"
		],
		"notes": "x"
  },
  {
    "name": "Pumpkin Cookie",
    "hp": 0,
    "hunger": 37.5,
    "sanity": 15,
		"rot": 10,
		"ismeat": false,
		"img": "./images/crockpot/pumpkincookie.png",
		"recipes": [
			["pumpkin", "honey", "honey", "any"],
			["pumpkin", "honey", "honey", "twigs"]
		],
		"restrictions": [
			"none"
		],
		"notes": "x"
  },
  {
    "name": "Ratatouille",
    "hp": 3,
    "hunger": 25,
    "sanity": 5,
		"rot": 15,
		"ismeat": false,
		"img": "./images/crockpot/ratatouille.png",
		"recipes": [
			["veggies", "any", "any", "any"],
			["veggies", "ice", "ice", "ice"]
		],
		"restrictions": [
			"meats", "dragonfruit", "twigs", "butterflywings"
		],
		"notes": "x"
  },
  {
    "name": "Salsa Fresca",
    "hp": 3,
    "hunger": 25,
    "sanity": 33,
		"rot": 15,
		"ismeat": false,
		"img": "./images/crockpot/salsafresca.png",
		"recipes": [
			["toma", "garlic", "any", "any"],
			["toma", "garlic", "ice", "ice"]
		],
		"restrictions": [
			"meats", "egg", "twigs"
		],
		"notes": "x"
  },
  {
    "name": "Seafood Gumbo",
    "hp": 40,
    "hunger": 37.5,
    "sanity": 20,
		"rot": 10,
		"ismeat": true,
		"img": "./images/crockpot/seafoodgumbo.png",
		"recipes": [
			["eel", "fishes", "any", "any"],
			["eel", "eel", "eel", "twigs"],
			["eel", "fishmorsel", "fishmorsel", "fishmorsel"]
		],
		"restrictions": [
			"none"
		],
		"notes": "x"
  },
  {
    "name": "Spicy Chili",
    "hp": 20,
    "hunger": 37.5,
    "sanity": 0,
		"rot": 10,
		"ismeat": true,
		"img": "./images/crockpot/spicychili.png",
		"recipes": [
			["meats", "meats", "veggies", "veggies"],
			["monstermeat", "freshwaterfish", "lichen", "lichen"],
			["monstermeat", "froglegs", "carrot", "carrot"]
		],
		"restrictions": [
			"none"
		],
		"notes": "x"
  },
  {
    "name": "Stuffed Eggplant",
    "hp": 3,
    "hunger": 37.5,
    "sanity": 15,
		"rot": 6,
		"ismeat": false,
		"img": "./images/crockpot/stuffedeggplant.png",
		"recipes": [
			["eggplant", "veggies", "any", "any"],
			["eggplant", "lichen", "twigs", "twigs"],
			["eggplant", "carrot", "berries", "berries"]
		],
		"restrictions": [
			"none"
		],
		"notes": "x"
  },
  {
    "name": "Stuffed Pepper Poppers",
    "hp": 30,
    "hunger": 25,
    "sanity": -5,
		"rot": 15,
		"ismeat": true,
		"img": "./images/crockpot/stuffedpepperpoppers.png",
		"recipes": [
			["pepper", "meats", "any", "any"],
			["pepper", "monstermeat", "berries", "berries"]
		],
		"restrictions": [
			"twigs"
		],
		"notes": "x"
  },
  {
    "name": "Surf n' Turf",
    "hp": 60,
    "hunger": 37.5,
    "sanity": 33,
		"rot": 10,
		"ismeat": true,
		"img": "./images/crockpot/surfnturf.png",
		"recipes": [
			["meats", "fishes", "any", "any"],
			["eel", "eel", "monstermeat", "monstermeat"]
		],
		"restrictions": [
			"ice"
		],
		"notes": "x"
  },
  {
    "name": "Taffy",
    "hp": -3,
    "hunger": 25,
    "sanity": 15,
		"rot": 15,
		"ismeat": false,
		"img": "./images/crockpot/taffy.png",
		"recipes": [
			["honey", "honey", "honey", "any"],
			["honey", "honey", "honey", "twigs"]
		],
		"restrictions": [
			"meats"
		],
		"notes": "x"
  },
  {
    "name": "Trail Mix",
    "hp": 30,
    "hunger": 12.5,
    "sanity": 5,
		"rot": 15,
		"ismeat": false,
		"img": "./images/crockpot/trailmix.png",
		"recipes": [
			["roastedbirchnut", "berries", "fruits", "any"],
			["roastedbirchnut", "berries", "berries", "twigs"]

		],
		"restrictions": [
			"meats", "veggies", "egg", "butter"
		],
		"notes": "x"
  },
  {
    "name": "Turkey Dinner",
    "hp": 20,
    "hunger": 75,
    "sanity": 5,
		"rot": 6,
		"ismeat": true,
		"img": "./images/crockpot/turkeydinner.png",
		"recipes": [
			["drumstick", "drumstick", "meats", "veggies"],
			["drumstick", "drumstick", "meats", "fruits"]
		],
		"restrictions": [
			"egg", "honey", "electricmilk", "twigs"
		],
		"notes": "x"
  },
  {
    "name": "Unagi",
    "hp": 20,
    "hunger": 18.75,
    "sanity": 5,
		"rot": 10,
		"ismeat": true,
		"img": "./images/crockpot/unagi.png",
		"recipes": [
			["eel", "lichen", "any", "any"],
			["eel", "lichen", "twigs", "twigs"],
			["eel", "lichen", "monstermeat", "monstermeat"]
		],
		"restrictions": [
			"none"
		],
		"notes": "x"
  },
  {
    "name": "Vegetable Stinger",
    "hp": 3,
    "hunger": 25,
    "sanity": 33,
		"rot": 15,
		"ismeat": false,
		"img": "./images/crockpot/vegetablestinger.png",
		"recipes": [
			["asparagus", "veggies", "veggies", "ice"],
			["toma", "veggies", "veggies", "ice"],
			["asparagus", "carrot", "redcap", "ice"]
		],
		"restrictions": [
			"none"
		],
		"notes": "x"
  },
  {
    "name": "Waffles",
    "hp": 60,
    "hunger": 37.5,
    "sanity": 5,
		"rot": 6,
		"ismeat": false,
		"img": "./images/crockpot/waffles.png",
		"recipes": [
			["butter", "berries", "egg", "any"],
			["butter", "berries", "egg", "twigs"]
		],
		"restrictions": [
			"meats"
		],
		"notes": "x"
  },
  {
    "name": "Wet Goop",
    "hp": 0,
    "hunger": 0,
    "sanity": 0,
		"rot": 6,
		"ismeat": false,
		"img": "./images/crockpot/wetgoop.png",
		"recipes": [
			["any", "any", "any", "any"],
			["twigs", "twigs", "twigs", "twigs"]
		],
		"restrictions": [
			"none"
		]
  }
]